{
    "player":[
        {
            "id": 1,
            "name": "Bent",
            "gamerTag": "Bensoiur",
            "email": "Ben4000@gmail.com",
            "phone": 30201040
        }
    ],
    "team":[
        {
            "id": 1,
            "name": "Team Turkiye",
            "owner": 1,
            "players": [{
                "id": 1,
            "name": "Bent",
            "gamerTag": "Bensoiur",
            "email": "Ben4000@gmail.com",
            "phone": 30201040
            }]
        }
    ],
    "match": [{
        "id": 1,
        "location": "Online",
        "date": "2023-03-01",
        "winner": 1,
        "score": [2,1],
        "stage": 3,
        "teams":[
            {
                "id": 1,
                "name": "Team Turkiye",
                "owner": 1,
                "players": [{
                    "id": 1,
                "name": "Bent",
                "gamerTag": "Bensoiur",
                "email": "Ben4000@gmail.com",
                "phone": 30201040
                }]
            },
            {
                "id": 2,
                "name": "Team USA",
                "owner": 2,
                "players": [{
                    "id": 2,
                "name": "James",
                "gamerTag": "JamieBear",
                "email": "Jammy@gmail.com",
                "phone": 60504030
                }]
            }
        ]
    }],
    "tournament": [{
        "id": 1,
        "startDate": "2023-03-01",
        "endDate": "2023-03-02",
        "tournamentType": 1,
        "gameType": "Rocket League",
        "tournamentWinner": 1,
        "maxTeams": 4,
        "minTeams": 2,
        "matches": [{
            "id": 1,
            "location": "Online",
            "date": "2023-03-01",
            "winner": 1,
            "score": [2,1],
            "stage": 3,
            "teams":[
                {
                    "id": 1,
                    "name": "Team Turkiye",
                    "owner": 1,
                    "players": [{
                        "id": 1,
                    "name": "Bent",
                    "gamerTag": "Bensoiur",
                    "email": "Ben4000@gmail.com",
                    "phone": 30201040
                    }]
                },
                {
                    "id": 2,
                    "name": "Team USA",
                    "owner": 2,
                    "players": [{
                        "id": 2,
                    "name": "James",
                    "gamerTag": "JamieBear",
                    "email": "Jammy@gmail.com",
                    "phone": 60504030
                    }]
                }
            ]
        }]
    }]
}